README.rst
setup.cfg
setup.py
billparser/__init__.py
billparser.egg-info/PKG-INFO
billparser.egg-info/SOURCES.txt
billparser.egg-info/dependency_links.txt
billparser.egg-info/entry_points.txt
billparser.egg-info/not-zip-safe
billparser.egg-info/requires.txt
billparser.egg-info/top_level.txt