Metadata-Version: 1.1
Name: billparser
Version: 0.1
Summary: Parse PDF files and extract fields based on definition files
Home-page: https://bitbucket.org/gnarvaja/billparser
Author: Guillermo M. Narvaja
Author-email: guillermo.narvaja@radiocut.fm
License: BSD
Platform: UNKNOWN
Classifier: Development Status :: 4 - Beta
Classifier: Intended Audience :: Developers
Classifier: License :: OSI Approved :: BSD License
Classifier: Natural Language :: English
Classifier: Programming Language :: Python :: 2.7
Classifier: Programming Language :: Python :: 3
